vntree/__init__.py
vntree/mongo.py
vntree/node.py
vntree-0.4.0.dist-info/LICENSE
vntree-0.4.0.dist-info/METADATA
vntree-0.4.0.dist-info/WHEEL
vntree-0.4.0.dist-info/top_level.txt
vntree-0.4.0.dist-info/RECORD
